[
  {
    "name": "a",
    "power": "super cringe",
    "universe": "DC"
  },
  {
    "name": "bobbbbb",
    "power": "P"
  },
  {
    "name": "Rob",
    "power": "Flower Power",
    "universe": "Marvel"
  },
  {
    "name": "aodsijf",
    "power": "dajfoi",
    "universe": "doisjg"
  },
  {
    "name": "Bradd",
    "power": "Poo",
    "universe": {}
  },
  {
    "name": "Bobby",
    "power": "Splendid",
    "universe": "DC"
  },
  {
    "name": "ala",
    "power": [
      "bomb"
    ],
    "universe": "aosidf"
  },
  {
    "name": "Timmy",
    "power": [
      "Strong",
      "Speed"
    ],
    "universe": "DC"
  }
]